poetry_dotenv/__init__.py
poetry_dotenv/dotenv/__init__.py
poetry_dotenv/dotenv/core.py
poetry_dotenv/dotenv/parsers.py
poetry_dotenv/dotenv/variables.py
poetry_dotenv/plugin.py
poetry_dotenv/py.typed
poetry_dotenv-0.3.0.dist-info/METADATA
poetry_dotenv-0.3.0.dist-info/entry_points.txt
poetry_dotenv-0.3.0.dist-info/WHEEL
poetry_dotenv-0.3.0.dist-info/LICENSE
poetry_dotenv-0.3.0.dist-info/RECORD
