Metadata-Version: 2.1
Name: poetry-dotenv
Version: 0.3.0
Summary: poetry-dotenv - is the plugin that automatically loads environment variables from a dotenv file into the environment before poetry commands are run.
Home-page: https://github.com/volopivoshenko/poetry-dotenv
License: MIT
Keywords: python,pypi,poetry,plugin,plugins,poetry-plugin,poetry-plugins,env,dotenv,cross-platform,hacktoberfest
Author: Volodymyr Pivoshenko
Author-email: volodymyr.pivoshenko@gmail.com
Maintainer: Volodymyr Pivoshenko
Maintainer-email: volodymyr.pivoshenko@gmail.com
Requires-Python: >=3.8,<4.0
Classifier: Development Status :: 5 - Production/Stable
Classifier: Environment :: Other Environment
Classifier: Intended Audience :: Developers
Classifier: Intended Audience :: Information Technology
Classifier: License :: OSI Approved :: MIT License
Classifier: Natural Language :: English
Classifier: Operating System :: OS Independent
Classifier: Programming Language :: Python
Classifier: Programming Language :: Python :: 3
Classifier: Programming Language :: Python :: 3.8
Classifier: Programming Language :: Python :: 3.9
Classifier: Programming Language :: Python :: 3.10
Classifier: Programming Language :: Python :: 3.11
Classifier: Programming Language :: Python :: 3
Classifier: Programming Language :: Python :: 3.10
Classifier: Programming Language :: Python :: 3.8
Classifier: Programming Language :: Python :: 3.9
Classifier: Topic :: Scientific/Engineering
Classifier: Topic :: Software Development
Classifier: Topic :: Software Development :: Libraries
Classifier: Topic :: Software Development :: Libraries :: Python Modules
Requires-Dist: poetry (>=1.3.2,<2.0.0)
Project-URL: Documentation, https://github.com/volopivoshenko/poetry-dotenv
Project-URL: Issues, https://github.com/volopivoshenko/poetry-dotenv/issues
Project-URL: Repository, https://github.com/volopivoshenko/poetry-dotenv
Project-URL: Releases, https://github.com/volopivoshenko/poetry-dotenv/releases
Project-URL: Say Thanks!, https://www.buymeacoffee.com/volopivoshenko
